weather_mcp/Weather.py
weather_mcp/__init__.py
weather_mcp_copa-0.1.0.dist-info/METADATA
weather_mcp_copa-0.1.0.dist-info/WHEEL
weather_mcp_copa-0.1.0.dist-info/entry_points.txt
weather_mcp_copa-0.1.0.dist-info/top_level.txt
weather_mcp_copa-0.1.0.dist-info/RECORD
