Metadata-Version: 2.4
Name: weather-mcp-copa
Version: 0.1.0
Summary: A FastMCP server for fetching weather alerts and forecasts from NWS API
Author: PKW
License: MIT
Requires-Python: >=3.10
Requires-Dist: httpx>=0.27.0
Requires-Dist: mcp>=0.1.0
